materialism/__init__.py
materialism/base.html
materialism/genindex.html
materialism/page.html
materialism/search.html
materialism/theme.conf
materialism/partials/_head.html
materialism/partials/_variables.jinja
materialism/partials/announce.html
materialism/partials/body-prefix.html
materialism/partials/body-suffix.html
materialism/partials/content.html
materialism/partials/footer.html
materialism/partials/header-tabs.html
materialism/partials/header.html
materialism/static/scripts/main.js
materialism/static/scripts/vendor/gumshoe.min.js
materialism/static/stylesheets/colour.css
materialism/static/stylesheets/main.css
materialism-0.1.2.dist-info/entry_points.txt
materialism-0.1.2.dist-info/LICENSE
materialism-0.1.2.dist-info/WHEEL
materialism-0.1.2.dist-info/METADATA
materialism-0.1.2.dist-info/RECORD
