Metadata-Version: 2.1
Name: materialism
Version: 0.1.2
Summary: A Material Design theme for Sphinx (inspired by mkdocs-material).
Home-page: https://github.com/pradyunsg/materialism
License: UNKNOWN
Author: Pradyun Gedam
Author-email: mail@pradyunsg.me
Requires-Python: >=3.5
Requires-Dist: sphinx ; extra == "doc"
Requires-Dist: pytest ; extra == "test"
Requires-Dist: pytest-cov ; extra == "test"
Requires-Dist: pytest-xdist ; extra == "test"
Provides-Extra: doc
Provides-Extra: test
